llama_index/tools/__init__.py
llama_index/tools/agentbay/__init__.py
llama_index/tools/agentbay/base.py
llama_index/tools/agentbay/browser_tools.py
llama_index/tools/agentbay/code_tools.py
llama_index/tools/agentbay/command_tools.py
llama_index/tools/agentbay/filesystem_tools.py
llama_index/tools/agentbay/output_parser.py
llama_index/tools/agentbay/rag_helper.py
llama_index_tools_agentbay-0.1.4.dist-info/METADATA
llama_index_tools_agentbay-0.1.4.dist-info/WHEEL
llama_index_tools_agentbay-0.1.4.dist-info/licenses/LICENSE
llama_index_tools_agentbay-0.1.4.dist-info/RECORD
