Metadata-Version: 2.4
Name: llama-index-tools-agentbay
Version: 0.1.4
Summary: AgentBay tools integration for LlamaIndex - provides browser automation, file operations, and command execution capabilities
License: MIT
License-File: LICENSE
Author: LlamaIndex Team
Requires-Python: >=3.8.1,<4.0.0
Classifier: License :: OSI Approved :: MIT License
Classifier: Programming Language :: Python :: 3
Classifier: Programming Language :: Python :: 3.9
Classifier: Programming Language :: Python :: 3.10
Classifier: Programming Language :: Python :: 3.11
Classifier: Programming Language :: Python :: 3.12
Classifier: Programming Language :: Python :: 3.13
Classifier: Programming Language :: Python :: 3.14
Requires-Dist: llama-index-core (>=0.14.0,<0.15.0)
Requires-Dist: wuying-agentbay-sdk (>=0.13.0,<0.14.0)
